{
	"partitions" : [
		{
			"name" : "Top",
			"pins" : [
				{
					"name" : "SUA",
					"strict" : false
				},
				{
					"name" : "SUB",
					"strict" : false
				},
				{
					"name" : "SUC",
					"strict" : false
				},
				{
					"name" : "SUD",
					"strict" : false
				},
				{
					"name" : "SUE",
					"strict" : false
				},
				{
					"name" : "SUF",
					"strict" : false
				},
				{
					"name" : "SUG",
					"strict" : false
				},
				{
					"name" : "SDA",
					"strict" : false
				},
				{
					"name" : "SDB",
					"strict" : false
				},
				{
					"name" : "SDC",
					"strict" : false
				},
				{
					"name" : "SDD",
					"strict" : false
				},
				{
					"name" : "SDE",
					"strict" : false
				},
				{
					"name" : "SDF",
					"strict" : false
				},
				{
					"name" : "SDG",
					"strict" : false
				},
				{
					"name" : "MUA",
					"strict" : false
				},
				{
					"name" : "MUB",
					"strict" : false
				},
				{
					"name" : "MUC",
					"strict" : false
				},
				{
					"name" : "MUD",
					"strict" : false
				},
				{
					"name" : "MUE",
					"strict" : false
				},
				{
					"name" : "MUF",
					"strict" : false
				},
				{
					"name" : "MUG",
					"strict" : false
				},
				{
					"name" : "MDA",
					"strict" : false
				},
				{
					"name" : "MDB",
					"strict" : false
				},
				{
					"name" : "MDC",
					"strict" : false
				},
				{
					"name" : "MDD",
					"strict" : false
				},
				{
					"name" : "MDE",
					"strict" : false
				},
				{
					"name" : "MDF",
					"strict" : false
				},
				{
					"name" : "MDG",
					"strict" : false
				},
				{
					"name" : "HUA",
					"strict" : false
				},
				{
					"name" : "HUB",
					"strict" : false
				},
				{
					"name" : "HUC",
					"strict" : false
				},
				{
					"name" : "HUD",
					"strict" : false
				},
				{
					"name" : "HUE",
					"strict" : false
				},
				{
					"name" : "HUF",
					"strict" : false
				},
				{
					"name" : "HUG",
					"strict" : false
				},
				{
					"name" : "HDB",
					"strict" : false
				},
				{
					"name" : "HDC",
					"strict" : false
				},
				{
					"name" : "HDD",
					"strict" : false
				},
				{
					"name" : "HDE",
					"strict" : false
				},
				{
					"name" : "HDF",
					"strict" : false
				},
				{
					"name" : "HDG",
					"strict" : false
				},
				{
					"name" : "HDA",
					"strict" : false
				},
				{
					"name" : "B1",
					"strict" : false
				},
				{
					"name" : "B2",
					"strict" : false
				},
				{
					"name" : "CK",
					"strict" : false
				}
			]
		}
	]
}